docker2mqtt/__docker__.py
docker2mqtt/__init__.py
docker2mqtt/__main__.py
docker2mqtt/const.py
docker2mqtt/docker2mqtt.py
docker2mqtt/exceptions.py
docker2mqtt/helpers.py
docker2mqtt/py.typed
docker2mqtt/type_definitions.py
docker2mqtt-2.5.4.dist-info/licenses/LICENSE
docker2mqtt-2.5.4.dist-info/METADATA
docker2mqtt-2.5.4.dist-info/WHEEL
docker2mqtt-2.5.4.dist-info/entry_points.txt
docker2mqtt-2.5.4.dist-info/top_level.txt
docker2mqtt-2.5.4.dist-info/RECORD
