Metadata-Version: 2.4
Name: docker2mqtt
Version: 2.5.4
Summary: Send your docker stats and and events to mqtt and discovery them in home assistant.
Author-email: Cyrill Raccaud <cyrill.raccaud+pypi@gmail.com>
License: MIT License
Project-URL: Documentation, https://miaucl.github.io/docker2mqtt/
Project-URL: Source, https://github.com/miaucl/docker2mqtt
Project-URL: Issues, https://github.com/miaucl/docker2mqtt/issues
Keywords: docker,mqtt,paho,home-assistant,system-monitoring,discovery,iot
Classifier: Programming Language :: Python :: 3
Classifier: License :: OSI Approved :: MIT License
Classifier: Operating System :: OS Independent
Classifier: Intended Audience :: Information Technology
Classifier: Topic :: System :: Monitoring
Classifier: Topic :: System :: Logging
Classifier: Topic :: System :: Systems Administration
Requires-Python: >=3.12
License-File: LICENSE
Requires-Dist: jsons
Requires-Dist: psutil
Requires-Dist: paho-mqtt
Requires-Dist: numpy
Requires-Dist: typing-extensions
Dynamic: license-file
